flask_allow/__init__.py
flask_allow/allow.py
flask_allow/exceptions.py
Flask_Allow-2.0.1.dist-info/METADATA
Flask_Allow-2.0.1.dist-info/WHEEL
Flask_Allow-2.0.1.dist-info/top_level.txt
Flask_Allow-2.0.1.dist-info/RECORD
