Metadata-Version: 2.1
Name: Flask-Allow
Version: 2.0.1
Summary: Flask-Allow allows white/black listing of ip addresses/networks and providing access log.
Home-page: https://github.com/pe2mbs/flask-allow
Author: Marc Bertens-Nguyen
Author-email: m.bertens@pe2mbs.nl
License: GPL 2.0-only
Keywords: flask,white,black,list,access
Classifier: Development Status :: 5 - Production/Stable
Classifier: License :: OSI Approved :: GNU General Public License v2 (GPLv2)
Classifier: Natural Language :: English
Classifier: Operating System :: OS Independent
Classifier: Programming Language :: Python :: 3.8
Classifier: Programming Language :: Python :: 3.9
Classifier: Programming Language :: Python :: 3.10
Classifier: Programming Language :: Python :: 3.11
Classifier: Programming Language :: Python :: Implementation :: CPython
Classifier: Environment :: Web Environment
Classifier: Framework :: Flask
Classifier: Topic :: Internet :: WWW/HTTP :: HTTP Servers
Classifier: Topic :: Internet :: WWW/HTTP :: WSGI
Classifier: Topic :: Security
Classifier: Topic :: System :: Logging
Classifier: Intended Audience :: Developers
Requires-Dist: flask ==2.3.3
Requires-Dist: mako ==1.3.0
